py_grafana_render/__init__.py
py_grafana_render/py.typed
py_grafana_render-0.1.11.dist-info/METADATA
py_grafana_render-0.1.11.dist-info/WHEEL
py_grafana_render-0.1.11.dist-info/RECORD
