Metadata-Version: 2.4
Name: py-grafana-render
Version: 0.1.11
Author-email: YiZixuan <sqkkyzx@qq.com>
Requires-Python: >=3.11
Requires-Dist: httpx
Requires-Dist: playwright
